LICENSE
MANIFEST.in
NOTICE
README.rst
setup.py
dj_revproxy.egg-info/PKG-INFO
dj_revproxy.egg-info/SOURCES.txt
dj_revproxy.egg-info/dependency_links.txt
dj_revproxy.egg-info/not-zip-safe
dj_revproxy.egg-info/requires.txt
dj_revproxy.egg-info/top_level.txt
example/testproxy/__init__.py
example/testproxy/__init__.pyc
example/testproxy/manage.py
example/testproxy/settings.py
example/testproxy/settings.pyc
example/testproxy/urls.py
example/testproxy/urls.pyc
revproxy/__init__.py
revproxy/proxy.py
revproxy/util.py