Metadata-Version: 1.0
Name: dj-revproxy
Version: 0.2.1
Summary: Django reverse proxy
Home-page: http://github.com/benoitc/dj-revproxy
Author: Benoit Chesneau
Author-email: benoitc@e-engura.org
License: BSD
Platform: UNKNOWN
Classifier: License :: OSI Approved :: MIT License
Classifier: Intended Audience :: Developers
Classifier: Intended Audience :: System Administrators
Classifier: Development Status :: 4 - Beta
Classifier: Programming Language :: Python
Classifier: Operating System :: OS Independent
Classifier: Topic :: Internet :: WWW/HTTP :: Dynamic Content
Classifier: Topic :: Software Development
Classifier: Topic :: Software Development :: Libraries :: Application Frameworks
